heysync/__init__.py
heysync/utils.py
heysync-1.0.1.dist-info/METADATA
heysync-1.0.1.dist-info/LICENSE
heysync-1.0.1.dist-info/WHEEL
heysync-1.0.1.dist-info/RECORD
