Metadata-Version: 2.1
Name: heysync
Version: 1.0.1
Summary: Hey, make async functions and classes sync
Home-page: https://github.com/oren0e/heysync
Keywords: Async,Async-to-Sync,Utility
Author: oren0e
Requires-Python: >=3.7,<4.0
Classifier: Programming Language :: Python :: 3
Classifier: Programming Language :: Python :: 3.7
Classifier: Programming Language :: Python :: 3.8
Classifier: Programming Language :: Python :: 3.9
Classifier: Programming Language :: Python :: 3.10
Classifier: Programming Language :: Python :: 3.11
Project-URL: Repository, https://github.com/oren0e/heysync
